AdvancedR/README.md
AdvancedR/__init__.py
AdvancedR/__main__.py
AdvancedR/file.epub
AdvancedR/index.html
AdvancedR/css/__init__.py
AdvancedR/css/annotations.css
AdvancedR/css/main.css
AdvancedR/css/normalize.css
AdvancedR/css/popup.css
AdvancedR/font/__init__.py
AdvancedR/font/fontello.eot
AdvancedR/font/fontello.svg
AdvancedR/font/fontello.ttf
AdvancedR/font/fontello.woff
AdvancedR/img/__init__.py
AdvancedR/img/annotator-glyph-sprite.png
AdvancedR/img/annotator-icon-sprite.png
AdvancedR/img/apple-touch-icon.png
AdvancedR/img/cancelfullscreen.png
AdvancedR/img/close.png
AdvancedR/img/fullscreen.png
AdvancedR/img/loader.gif
AdvancedR/img/menu-icon.png
AdvancedR/img/save.png
AdvancedR/img/saved.png
AdvancedR/img/settings-s.png
AdvancedR/img/settings.png
AdvancedR/img/star.png
AdvancedR/js/__init__.py
AdvancedR/js/epub.js
AdvancedR/js/epub.min.js
AdvancedR/js/epub.min.map
AdvancedR/js/hooks.min.js
AdvancedR/js/hooks.min.map
AdvancedR/js/reader.js
AdvancedR/js/reader.js.map
AdvancedR/js/reader.min.js
AdvancedR/js/reader.min.map
AdvancedR/js/hooks/__init__.py
AdvancedR/js/hooks/extensions/__init__.py
AdvancedR/js/hooks/extensions/highlight.js
AdvancedR/js/libs/__init__.py
AdvancedR/js/libs/jquery.min.js
AdvancedR/js/libs/localforage.min.js
AdvancedR/js/libs/screenfull.js
AdvancedR/js/libs/screenfull.min.js
AdvancedR/js/libs/zip.min.js
AdvancedR/js/plugins/__init__.py
AdvancedR/js/plugins/hypothesis.js
AdvancedR/js/plugins/search.js
advanced_r-2024.3.3.0.dist-info/METADATA
advanced_r-2024.3.3.0.dist-info/WHEEL
advanced_r-2024.3.3.0.dist-info/entry_points.txt
advanced_r-2024.3.3.0.dist-info/top_level.txt
advanced_r-2024.3.3.0.dist-info/RECORD
